{
    "type": "FeatureCollection",
    "features": [
        {
            "type": "Feature",
            "geometry": {
                "type": "MultiPolygon",
                "coordinates": [
                    [
                        [
                            [
                                120.19874927303,
                                23.379866369056
                            ],
                            [
                                120.19874355176,
                                23.379177399879
                            ],
                            [
                                120.19874277402,
                                23.379150514665
                            ],
                            [
                                120.19863663189,
                                23.379149537302
                            ],
                            [
                                120.19863893325,
                                23.378688666071
                            ],
                            [
                                120.19857133764,
                                23.378135520215
                            ],
                            [
                                120.19888252124,
                                23.378170932693
                            ],
                            [
                                120.19887476403,
                                23.378523817535
                            ],
                            [
                                120.19891396996,
                                23.379111936888
                            ],
                            [
                                120.19903971302,
                                23.379133825717
                            ],
                            [
                                120.19905336791,
                                23.379206301539
                            ],
                            [
                                120.19920698539,
                                23.379982741694
                            ],
                            [
                                120.19921593593,
                                23.380056494116
                            ],
                            [
                                120.1987509629,
                                23.380132155004
                            ],
                            [
                                120.19874927303,
                                23.379866369056
                            ]
                        ]
                    ]
                ]
            },
            "properties": {
                "縣市": "嘉義縣",
                "鄉鎮": "布袋鎮",
                "地段": "上江山段",
                "段號": 6360000,
                "id": "QB1442",
                "ymax": 23.380132155004,
                "ymin": 23.378135520215,
                "xmax": 120.19921593593,
                "xmin": 120.19857133764,
                "xcenter": 120.198893636785,
                "ycenter": 23.3791338376095,
                "area_id": "QB",
                "section_id": "1442",
                "land_id": 6360000,
                "query_log": [],
                "query": "嘉義縣,上江山段,636"
            }
        }
    ],
    "notfound": []
}