{
    "type": "FeatureCollection",
    "features": [
        {
            "type": "Feature",
            "geometry": {
                "type": "MultiPolygon",
                "coordinates": [
                    [
                        [
                            [
                                120.19823570614,
                                23.375761747948
                            ],
                            [
                                120.19863142103,
                                23.37564150944
                            ],
                            [
                                120.19908746092,
                                23.375642977958
                            ],
                            [
                                120.19920659694,
                                23.375669602012
                            ],
                            [
                                120.19927035019,
                                23.375689872525
                            ],
                            [
                                120.19922093376,
                                23.37633216796
                            ],
                            [
                                120.19917584407,
                                23.37633237069
                            ],
                            [
                                120.19885941128,
                                23.37584255232
                            ],
                            [
                                120.1985893739,
                                23.376073128137
                            ],
                            [
                                120.19837727966,
                                23.37604039086
                            ],
                            [
                                120.19823570614,
                                23.375761747948
                            ]
                        ]
                    ]
                ]
            },
            "properties": {
                "縣市": "嘉義縣",
                "鄉鎮": "布袋鎮",
                "地段": "上江山段",
                "段號": 8960000,
                "id": "QB1442",
                "ymax": 23.37633237069,
                "ymin": 23.37564150944,
                "xmax": 120.19927035019,
                "xmin": 120.19823570614,
                "xcenter": 120.198753028165,
                "ycenter": 23.375986940065,
                "area_id": "QB",
                "section_id": "1442",
                "land_id": 8960000,
                "query_log": [],
                "query": "嘉義縣,上江山段,896"
            }
        }
    ],
    "notfound": []
}