{
    "type": "FeatureCollection",
    "features": [
        {
            "type": "Feature",
            "geometry": {
                "type": "MultiPolygon",
                "coordinates": [
                    [
                        [
                            [
                                120.20500590354,
                                23.378297127598
                            ],
                            [
                                120.20534549183,
                                23.378295384721
                            ],
                            [
                                120.20538397516,
                                23.379167053369
                            ],
                            [
                                120.20500355458,
                                23.379163385916
                            ],
                            [
                                120.20500590354,
                                23.378297127598
                            ]
                        ]
                    ]
                ]
            },
            "properties": {
                "縣市": "嘉義縣",
                "鄉鎮": "布袋鎮",
                "地段": "上江山段",
                "段號": 3760000,
                "id": "QB1442",
                "ymax": 23.379167053369,
                "ymin": 23.378295384721,
                "xmax": 120.20538397516,
                "xmin": 120.20500355458,
                "xcenter": 120.20519376487,
                "ycenter": 23.378731219045,
                "area_id": "QB",
                "section_id": "1442",
                "land_id": 3760000,
                "query_log": [],
                "query": "嘉義縣,上江山段,376"
            }
        }
    ],
    "notfound": []
}