{
    "type": "FeatureCollection",
    "features": [
        {
            "type": "Feature",
            "geometry": {
                "type": "MultiPolygon",
                "coordinates": [
                    [
                        [
                            [
                                120.19993809452,
                                23.374223925512
                            ],
                            [
                                120.19994667831,
                                23.374202290983
                            ],
                            [
                                120.20001005754,
                                23.374049998977
                            ],
                            [
                                120.20010817861,
                                23.373665058245
                            ],
                            [
                                120.20027939461,
                                23.373700185549
                            ],
                            [
                                120.20030753968,
                                23.373705965821
                            ],
                            [
                                120.20031097025,
                                23.373682137083
                            ],
                            [
                                120.20040328546,
                                23.373716860894
                            ],
                            [
                                120.20027600903,
                                23.374029680391
                            ],
                            [
                                120.20026311783,
                                23.374064733544
                            ],
                            [
                                120.20020124032,
                                23.374279900783
                            ],
                            [
                                120.19992761651,
                                23.374248151761
                            ],
                            [
                                120.19993809452,
                                23.374223925512
                            ]
                        ]
                    ]
                ]
            },
            "properties": {
                "縣市": "嘉義縣",
                "鄉鎮": "布袋鎮",
                "地段": "上江山段",
                "段號": 10190000,
                "id": "QB1442",
                "ymax": 23.374279900783,
                "ymin": 23.373665058245,
                "xmax": 120.20040328546,
                "xmin": 120.19992761651,
                "xcenter": 120.200165450985,
                "ycenter": 23.373972479514002,
                "area_id": "QB",
                "section_id": "1442",
                "land_id": 10190000,
                "query_log": [],
                "query": "嘉義縣,上江山段,1019"
            }
        }
    ],
    "notfound": []
}