{
    "type": "FeatureCollection",
    "features": [
        {
            "type": "Feature",
            "geometry": {
                "type": "MultiPolygon",
                "coordinates": [
                    [
                        [
                            [
                                120.20025460975,
                                23.412802169349
                            ],
                            [
                                120.19998509338,
                                23.412125595755
                            ],
                            [
                                120.19993803821,
                                23.41192199695
                            ],
                            [
                                120.19986881523,
                                23.411802255405
                            ],
                            [
                                120.19984479247,
                                23.411679889173
                            ],
                            [
                                120.1998072629,
                                23.411539174403
                            ],
                            [
                                120.19965117986,
                                23.411041976114
                            ],
                            [
                                120.19959427693,
                                23.410726365678
                            ],
                            [
                                120.19949675843,
                                23.41047452489
                            ],
                            [
                                120.19943075152,
                                23.410334806582
                            ],
                            [
                                120.19937930371,
                                23.410244288629
                            ],
                            [
                                120.19934105983,
                                23.410119564521
                            ],
                            [
                                120.19939939453,
                                23.410094158085
                            ],
                            [
                                120.19940982367,
                                23.410109634732
                            ],
                            [
                                120.19956243943,
                                23.410051008716
                            ],
                            [
                                120.19965801164,
                                23.410317691483
                            ],
                            [
                                120.19970506122,
                                23.410316218788
                            ],
                            [
                                120.20005536654,
                                23.41155586809
                            ],
                            [
                                120.20019826056,
                                23.41198216596
                            ],
                            [
                                120.20066495915,
                                23.413321803651
                            ],
                            [
                                120.20044573005,
                                23.413340674888
                            ],
                            [
                                120.20025460975,
                                23.412802169349
                            ]
                        ]
                    ]
                ]
            },
            "properties": {
                "縣市": "嘉義縣",
                "鄉鎮": "布袋鎮",
                "地段": "過溝新段",
                "段號": 5190000,
                "id": "QB1454",
                "ymax": 23.413340674888,
                "ymin": 23.410051008716,
                "xmax": 120.20066495915,
                "xmin": 120.19934105983,
                "xcenter": 120.20000300949,
                "ycenter": 23.411695841802,
                "area_id": "QB",
                "section_id": "1454",
                "land_id": 5190000,
                "query_log": [],
                "query": "嘉義縣,過溝新段,519"
            }
        }
    ],
    "notfound": []
}