{
    "type": "FeatureCollection",
    "features": [
        {
            "type": "Feature",
            "geometry": {
                "type": "MultiPolygon",
                "coordinates": [
                    [
                        [
                            [
                                120.20969279964,
                                23.379243905277
                            ],
                            [
                                120.20993445238,
                                23.379244413446
                            ],
                            [
                                120.2099397447,
                                23.379263326718
                            ],
                            [
                                120.20971284456,
                                23.379313851117
                            ],
                            [
                                120.20969279964,
                                23.379243905277
                            ]
                        ]
                    ],
                    [
                        [
                            [
                                120.20940830501,
                                23.378200857088
                            ],
                            [
                                120.20962229219,
                                23.378114276502
                            ],
                            [
                                120.2099352561,
                                23.379239072259
                            ],
                            [
                                120.20969591738,
                                23.379238932135
                            ],
                            [
                                120.20940830501,
                                23.378200857088
                            ]
                        ]
                    ]
                ]
            },
            "properties": {
                "縣市": "嘉義縣",
                "鄉鎮": "義竹鄉",
                "地段": "龍蛟潭段龍蛟小段",
                "段號": 11510001,
                "id": "QB0321",
                "ymax": 23.379313851117,
                "ymin": 23.378114276502,
                "xmax": 120.2099397447,
                "xmin": 120.20940830501,
                "xcenter": 120.20967402485499,
                "ycenter": 23.3787140638095,
                "area_id": "QB",
                "section_id": "0321",
                "land_id": 11510001,
                "query_log": [],
                "query": "嘉義縣,龍蛟潭段龍蛟小段,1151-1"
            }
        }
    ],
    "notfound": []
}