{
    "type": "FeatureCollection",
    "features": [
        {
            "type": "Feature",
            "geometry": {
                "type": "MultiPolygon",
                "coordinates": [
                    [
                        [
                            [
                                120.23182545326,
                                23.238082462976
                            ],
                            [
                                120.23210064996,
                                23.238083808075
                            ],
                            [
                                120.23212408766,
                                23.238113922465
                            ],
                            [
                                120.23194668588,
                                23.238299872711
                            ],
                            [
                                120.23182545326,
                                23.238082462976
                            ]
                        ]
                    ],
                    [
                        [
                            [
                                120.23181369932,
                                23.238073541923
                            ],
                            [
                                120.2317121923,
                                23.237890319276
                            ],
                            [
                                120.2317787809,
                                23.237857917723
                            ],
                            [
                                120.23182482841,
                                23.237804961281
                            ],
                            [
                                120.23188515557,
                                23.237835256039
                            ],
                            [
                                120.2319372773,
                                23.237881192409
                            ],
                            [
                                120.2320888999,
                                23.238074205245
                            ],
                            [
                                120.23181369932,
                                23.238073541923
                            ]
                        ]
                    ]
                ]
            },
            "properties": {
                "縣市": "臺南市",
                "鄉鎮": "下營區",
                "地段": "大屯寮段",
                "段號": 28180000,
                "id": "RC0316",
                "ymax": 23.238299872711,
                "ymin": 23.237804961281,
                "xmax": 120.23212408766,
                "xmin": 120.2317121923,
                "xcenter": 120.23191813998,
                "ycenter": 23.238052416996,
                "area_id": "RC",
                "section_id": "0316",
                "land_id": 28180000,
                "query_log": [],
                "query": "臺南市,大屯寮段,2818"
            }
        }
    ],
    "notfound": []
}