{
    "type": "FeatureCollection",
    "features": [
        {
            "type": "Feature",
            "geometry": {
                "type": "MultiPolygon",
                "coordinates": [
                    [
                        [
                            [
                                120.18433383427,
                                23.243207678866
                            ],
                            [
                                120.18407772235,
                                23.242377559322
                            ],
                            [
                                120.18417673383,
                                23.24235019077
                            ],
                            [
                                120.18434565355,
                                23.242290495021
                            ],
                            [
                                120.18463675098,
                                23.243356356618
                            ],
                            [
                                120.18466430552,
                                23.243444955131
                            ],
                            [
                                120.18466611178,
                                23.243490153733
                            ],
                            [
                                120.18462089324,
                                23.243568759833
                            ],
                            [
                                120.18458420864,
                                23.243612797188
                            ],
                            [
                                120.18432948532,
                                23.243409565594
                            ],
                            [
                                120.18417635246,
                                23.243268395436
                            ],
                            [
                                120.18433383427,
                                23.243207678866
                            ]
                        ]
                    ]
                ]
            },
            "properties": {
                "縣市": "臺南市",
                "鄉鎮": "學甲區",
                "地段": "學甲段",
                "段號": 19040000,
                "id": "RD0550",
                "ymax": 23.243612797188,
                "ymin": 23.242290495021,
                "xmax": 120.18466611178,
                "xmin": 120.18407772235,
                "xcenter": 120.184371917065,
                "ycenter": 23.2429516461045,
                "area_id": "RD",
                "section_id": "0550",
                "land_id": 19040000,
                "query_log": [],
                "query": "臺南市,學甲段,1904"
            }
        }
    ],
    "notfound": []
}