{
    "type": "FeatureCollection",
    "features": [
        {
            "type": "Feature",
            "geometry": {
                "type": "MultiPolygon",
                "coordinates": [
                    [
                        [
                            [
                                120.17677178301,
                                23.255726007634
                            ],
                            [
                                120.17677190107,
                                23.255706778849
                            ],
                            [
                                120.17677906681,
                                23.255726045816
                            ],
                            [
                                120.17677178301,
                                23.255726007634
                            ]
                        ]
                    ],
                    [
                        [
                            [
                                120.17643948732,
                                23.255444477549
                            ],
                            [
                                120.17646127138,
                                23.255116730467
                            ],
                            [
                                120.17667187317,
                                23.255728368274
                            ],
                            [
                                120.17667174918,
                                23.255748558497
                            ],
                            [
                                120.176540688,
                                23.25574017956
                            ],
                            [
                                120.17643948732,
                                23.255444477549
                            ]
                        ]
                    ]
                ]
            },
            "properties": {
                "縣市": "臺南市",
                "鄉鎮": "學甲區",
                "地段": "學甲段",
                "段號": 6810002,
                "id": "RD0550",
                "ymax": 23.255748558497,
                "ymin": 23.255116730467,
                "xmax": 120.17677906681,
                "xmin": 120.17643948732,
                "xcenter": 120.176609277065,
                "ycenter": 23.255432644482,
                "area_id": "RD",
                "section_id": "0550",
                "land_id": 6810002,
                "query_log": [],
                "query": "臺南市,學甲段,681-2"
            }
        }
    ],
    "notfound": []
}