{
    "type": "FeatureCollection",
    "features": [
        {
            "type": "Feature",
            "geometry": {
                "type": "MultiPolygon",
                "coordinates": [
                    [
                        [
                            [
                                120.20992384864,
                                23.220693018919
                            ],
                            [
                                120.2084520901,
                                23.220723951398
                            ],
                            [
                                120.20841309628,
                                23.219384523772
                            ],
                            [
                                120.20930120253,
                                23.219394826092
                            ],
                            [
                                120.20988004747,
                                23.219401902847
                            ],
                            [
                                120.20992384864,
                                23.220693018919
                            ]
                        ]
                    ]
                ]
            },
            "properties": {
                "縣市": "臺南市",
                "鄉鎮": "學甲區",
                "地段": "宅子港段",
                "段號": 1750060,
                "id": "RD0554",
                "ymax": 23.220723951398,
                "ymin": 23.219384523772,
                "xmax": 120.20992384864,
                "xmin": 120.20841309628,
                "xcenter": 120.20916847246,
                "ycenter": 23.220054237585,
                "area_id": "RD",
                "section_id": "0554",
                "land_id": 1750060,
                "query_log": [],
                "query": "臺南市,宅子港段,175-60"
            }
        }
    ],
    "notfound": []
}