{
    "type": "FeatureCollection",
    "features": [
        {
            "type": "Feature",
            "geometry": {
                "type": "MultiPolygon",
                "coordinates": [
                    [
                        [
                            [
                                120.19617416755,
                                23.238405790725
                            ],
                            [
                                120.19631320801,
                                23.238379000733
                            ],
                            [
                                120.19641255966,
                                23.238353674389
                            ],
                            [
                                120.19652364453,
                                23.238326741238
                            ],
                            [
                                120.19655706066,
                                23.238318578404
                            ],
                            [
                                120.19689821661,
                                23.238273653697
                            ],
                            [
                                120.19689969101,
                                23.238328663655
                            ],
                            [
                                120.19685365981,
                                23.238335095344
                            ],
                            [
                                120.19673088165,
                                23.238356968734
                            ],
                            [
                                120.19655390122,
                                23.238394398918
                            ],
                            [
                                120.19628029432,
                                23.23845383568
                            ],
                            [
                                120.19617288137,
                                23.23846995363
                            ],
                            [
                                120.19592646273,
                                23.238507027864
                            ],
                            [
                                120.1959204648,
                                23.238454494869
                            ],
                            [
                                120.19617416755,
                                23.238405790725
                            ]
                        ]
                    ]
                ]
            },
            "properties": {
                "縣市": "臺南市",
                "鄉鎮": "學甲區",
                "地段": "宅子港段",
                "段號": 3530006,
                "id": "RD0554",
                "ymax": 23.238507027864,
                "ymin": 23.238273653697,
                "xmax": 120.19689969101,
                "xmin": 120.1959204648,
                "xcenter": 120.196410077905,
                "ycenter": 23.238390340780498,
                "area_id": "RD",
                "section_id": "0554",
                "land_id": 3530006,
                "query_log": [],
                "query": "臺南市,宅子港段,353-6"
            }
        }
    ],
    "notfound": []
}