{
    "type": "FeatureCollection",
    "features": [
        {
            "type": "Feature",
            "geometry": {
                "type": "MultiPolygon",
                "coordinates": [
                    [
                        [
                            [
                                120.21122461311,
                                23.277926226744
                            ],
                            [
                                120.21126312165,
                                23.278194039127
                            ],
                            [
                                120.2111975945,
                                23.278248517307
                            ],
                            [
                                120.21118510184,
                                23.27819167192
                            ],
                            [
                                120.21113007686,
                                23.278005740931
                            ],
                            [
                                120.21122461311,
                                23.277926226744
                            ]
                        ]
                    ]
                ]
            },
            "properties": {
                "縣市": "臺南市",
                "鄉鎮": "鹽水區",
                "地段": "飯店段",
                "段號": 15420001,
                "id": "RA0021",
                "ymax": 23.278248517307,
                "ymin": 23.277926226744,
                "xmax": 120.21126312165,
                "xmin": 120.21113007686,
                "xcenter": 120.211196599255,
                "ycenter": 23.2780873720255,
                "area_id": "RA",
                "section_id": "0021",
                "land_id": 15420001,
                "query_log": [],
                "query": "臺南市,飯店段,1542-1"
            }
        }
    ],
    "notfound": []
}